{
  "1": {
    "id": 198,
    "version": 1,
    "name": "Staff of The Sage",
    "element": "earth",
    "type": "item",
    "duration": "equip",
    "cost": {
      "earth": 2
    },
    "attack": null,
    "health": null,
    "text": "Equip to a friendly creature. It gains +2 / +1 and \"when this attacks and destroys a creature, <search> for 'Sage Brennas'\"."
  },
  "2": {
    "id": 198,
    "version": 2,
    "name": "Staff of The Sage",
    "element": "earth",
    "type": "item",
    "duration": "equip",
    "cost": {
      "earth": 1
    },
    "attack": null,
    "health": null,
    "text": "Equip to a friendly creature. It gains +2 / +1 and \"when this attacks and destroys a creature, <search> for 'Sage Brennas'\"."
  }
}
